[
  {
    "name": "Run It",
    "link": "https://music.163.com/song?id=1408825563",
    "duration": "03:39",
    "artists": [
      {
        "name": "Midnight Kids",
        "link": "https://music.163.com/artist?id=13192314"
      },
      {
        "name": "Annika Wells",
        "link": "https://music.163.com/artist?id=12108797"
      }
    ],
    "album": {
      "name": "Run It",
      "link": "https://music.163.com/album?id=84008492"
    }
  },
  {
    "name": "don't care",
    "link": "https://music.163.com/song?id=1419439282",
    "duration": "03:09",
    "artists": [
      { "name": "NATIIVE", "link": "https://music.163.com/artist?id=13775064" },
      {
        "name": "Danni Carra",
        "link": "https://music.163.com/artist?id=32029983"
      }
    ],
    "album": {
      "name": "don't care",
      "link": "https://music.163.com/album?id=85303662"
    }
  },
  {
    "name": "So Into You",
    "link": "https://music.163.com/song?id=1357816082",
    "duration": "03:02",
    "artists": [
      {
        "name": "My Buddy Mike",
        "link": "https://music.163.com/artist?id=12260229"
      },
      {
        "name": "Love Alexa",
        "link": "https://music.163.com/artist?id=29433871"
      }
    ],
    "album": {
      "name": "So Into You ",
      "link": "https://music.163.com/album?id=78424448"
    }
  },
  {
    "name": "Words Of Love (Numa Numa)",
    "link": "https://music.163.com/song?id=1425225470",
    "duration": "03:09",
    "artists": [
      {
        "name": "Different Heaven",
        "link": "https://music.163.com/artist?id=1049917"
      },
      { "name": "Lost Boy", "link": "https://music.163.com/artist?id=12279141" }
    ],
    "album": {
      "name": "Colors EP",
      "link": "https://music.163.com/album?id=85925170"
    }
  },
  {
    "name": "I Can't Breath (Original Mix)",
    "link": "https://music.163.com/song?id=1449774005",
    "duration": "03:22",
    "artists": [
      { "name": "Taiga", "link": "https://music.163.com/artist?id=13177969" }
    ],
    "album": {
      "name": "I Can't Breath",
      "link": "https://music.163.com/album?id=89749038"
    }
  },
  {
    "name": "Coming Back",
    "link": "https://music.163.com/song?id=1360758772",
    "duration": "02:57",
    "artists": [
      {
        "name": "THEDETSTRIKE",
        "link": "https://music.163.com/artist?id=12628313"
      }
    ],
    "album": {
      "name": "Coming Back",
      "link": "https://music.163.com/album?id=78716502"
    }
  },
  {
    "name": "Room Service",
    "link": "https://music.163.com/song?id=1294165733",
    "duration": "02:13",
    "artists": [
      {
        "name": "Emily Vaughn",
        "link": "https://music.163.com/artist?id=12049240"
      }
    ],
    "album": {
      "name": "Room Service",
      "link": "https://music.163.com/album?id=71866701"
    }
  },
  {
    "name": "Broken Ones (Last Heroes Remix)",
    "link": "https://music.163.com/song?id=1448420680",
    "duration": "03:18",
    "artists": [
      { "name": "ILLENIUM", "link": "https://music.163.com/artist?id=1050518" },
      {
        "name": "Last Heroes",
        "link": "https://music.163.com/artist?id=11987034"
      },
      {
        "name": "Anna Clendening",
        "link": "https://music.163.com/artist?id=12533901"
      }
    ],
    "album": {
      "name": "ASCEND (Remixes)",
      "link": "https://music.163.com/album?id=89513700"
    }
  },
  {
    "name": "Not So Bad in LA",
    "link": "https://music.163.com/song?id=1314126165",
    "duration": "02:50",
    "artists": [
      { "name": "Allie X", "link": "https://music.163.com/artist?id=973030" }
    ],
    "album": {
      "name": "Super Sunset",
      "link": "https://music.163.com/album?id=73718954"
    }
  },
  {
    "name": "White Mercedes",
    "link": "https://music.163.com/song?id=1390487337",
    "duration": "03:23",
    "artists": [
      { "name": "Charli XCX", "link": "https://music.163.com/artist?id=53092" }
    ],
    "album": {
      "name": "Charli",
      "link": "https://music.163.com/album?id=81593693"
    }
  },
  {
    "name": "HUSHH",
    "link": "https://music.163.com/song?id=1379843871",
    "duration": "03:00",
    "artists": [
      { "name": "AViVA", "link": "https://music.163.com/artist?id=12074178" }
    ],
    "album": {
      "name": "HUSHH",
      "link": "https://music.163.com/album?id=80585287"
    }
  },
  {
    "name": "We're Not Alone (Original Mix)",
    "link": "https://music.163.com/song?id=28925189",
    "duration": "04:53",
    "artists": [
      {
        "name": "Virtual Riot",
        "link": "https://music.163.com/artist?id=813244"
      }
    ],
    "album": {
      "name": "We're Not Alone EP",
      "link": "https://music.163.com/album?id=2949170"
    }
  },
  {
    "name": "Closer",
    "link": "https://music.163.com/song?id=557579499",
    "duration": "04:12",
    "artists": [
      { "name": "Au5", "link": "https://music.163.com/artist?id=359309" },
      {
        "name": "Danyka Nadeau",
        "link": "https://music.163.com/artist?id=1078277"
      }
    ],
    "album": {
      "name": "Closer",
      "link": "https://music.163.com/album?id=38592191"
    }
  },
  {
    "name": "Too Cool",
    "link": "https://music.163.com/song?id=1343648547",
    "duration": "03:05",
    "artists": [
      {
        "name": "Emily Burns",
        "link": "https://music.163.com/artist?id=12234023"
      }
    ],
    "album": {
      "name": "Too Cool",
      "link": "https://music.163.com/album?id=75415432"
    }
  },
  {
    "name": "Save Me",
    "link": "https://music.163.com/song?id=477250181",
    "duration": "04:08",
    "artists": [
      {
        "name": "Zero Venture",
        "link": "https://music.163.com/artist?id=1150141"
      },
      {
        "name": "telepathics",
        "link": "https://music.163.com/artist?id=12279871"
      }
    ],
    "album": {
      "name": "Save Me",
      "link": "https://music.163.com/album?id=35456543"
    }
  },
  {
    "name": "Rolling Dice (Last Heroes Remix)",
    "link": "https://music.163.com/song?id=453492007",
    "duration": "03:26",
    "artists": [
      {
        "name": "Last Heroes",
        "link": "https://music.163.com/artist?id=11987034"
      },
      {
        "name": "Just A Gent",
        "link": "https://music.163.com/artist?id=893239"
      }
    ],
    "album": {
      "name": "Rolling Dice (Last Heroes Remix)",
      "link": "https://music.163.com/album?id=35123625"
    }
  },
  {
    "name": "Those Eyes (Original Mix)",
    "link": "https://music.163.com/song?id=17867243",
    "duration": "04:47",
    "artists": [
      { "name": "Feint", "link": "https://music.163.com/artist?id=93062" }
    ],
    "album": {
      "name": "Feint EP2",
      "link": "https://music.163.com/album?id=1644798"
    }
  },
  {
    "name": "Love Me Like You Used To",
    "link": "https://music.163.com/song?id=1375240947",
    "duration": "03:04",
    "artists": [
      {
        "name": "Savannah Sgro",
        "link": "https://music.163.com/artist?id=31381918"
      }
    ],
    "album": {
      "name": "Phobia",
      "link": "https://music.163.com/album?id=80116504"
    }
  },
  {
    "name": "Crash",
    "link": "https://music.163.com/song?id=533018657",
    "duration": "03:46",
    "artists": [
      { "name": "Neovaii", "link": "https://music.163.com/artist?id=12356095" }
    ],
    "album": {
      "name": "Onward",
      "link": "https://music.163.com/album?id=37374496"
    }
  },
  {
    "name": "Long Way Home (Last Heroes Remix)",
    "link": "https://music.163.com/song?id=1422606666",
    "duration": "03:30",
    "artists": [
      { "name": "Tritonal", "link": "https://music.163.com/artist?id=104133" },
      { "name": "HALIENE", "link": "https://music.163.com/artist?id=13202710" },
      { "name": "Schala", "link": "https://music.163.com/artist?id=11995110" },
      { "name": "Jorza", "link": "https://music.163.com/artist?id=12594166" },
      {
        "name": "Last Heroes",
        "link": "https://music.163.com/artist?id=11987034"
      }
    ],
    "album": {
      "name": "Long Way Home (Remixes)",
      "link": "https://music.163.com/album?id=85647445"
    }
  },
  {
    "name": "Hang Limb",
    "link": "https://music.163.com/song?id=1418510709",
    "duration": "04:39",
    "artists": [
      { "name": "Glacier", "link": "https://music.163.com/artist?id=860352" }
    ],
    "album": {
      "name": "Temple Inward",
      "link": "https://music.163.com/album?id=85175335"
    }
  },
  {
    "name": "Pagoda",
    "link": "https://music.163.com/song?id=1325892124",
    "duration": "05:10",
    "artists": [
      { "name": "Xomu", "link": "https://music.163.com/artist?id=12903205" },
      { "name": "Amidst", "link": "https://music.163.com/artist?id=12715779" }
    ],
    "album": {
      "name": "Pagoda",
      "link": "https://music.163.com/album?id=74395409"
    }
  },
  {
    "name": "In Your Wake (feat. Jeza) (Original Mix)",
    "link": "https://music.163.com/song?id=30394423",
    "duration": "05:28",
    "artists": [
      {
        "name": "Said The Sky",
        "link": "https://music.163.com/artist?id=1026094"
      },
      { "name": "ILLENIUM", "link": "https://music.163.com/artist?id=1050518" }
    ],
    "album": {
      "name": "In Your Wake (feat. Jeza)",
      "link": "https://music.163.com/album?id=3098520"
    }
  },
  {
    "name": "Time Is Running Out",
    "link": "https://music.163.com/song?id=571175220",
    "duration": "03:22",
    "artists": [
      {
        "name": "Why Mona",
        "link": "https://music.163.com/artist?id=15008055"
      },
      {
        "name": "Unlike Pluto",
        "link": "https://music.163.com/artist?id=860945"
      },
      {
        "name": "Joanna Jones",
        "link": "https://music.163.com/artist?id=13932656"
      }
    ],
    "album": {
      "name": "Time Is Running Out",
      "link": "https://music.163.com/album?id=39578392"
    }
  },
  {
    "name": "Breakdown VIP",
    "link": "https://music.163.com/song?id=28661112",
    "duration": "03:54",
    "artists": [
      { "name": "Noisestorm", "link": "https://music.163.com/artist?id=98081" }
    ],
    "album": {
      "name": "Breakdown VIP",
      "link": "https://music.163.com/album?id=2866223"
    }
  },
  {
    "name": "Stuck In Dreams",
    "link": "https://music.163.com/song?id=35920537",
    "duration": "04:07",
    "artists": [
      { "name": "Nightcall", "link": "https://music.163.com/artist?id=1083067" }
    ],
    "album": {
      "name": "Stuck In Dreams",
      "link": "https://music.163.com/album?id=3367502"
    }
  },
  {
    "name": "Golden",
    "link": "https://music.163.com/song?id=1436385192",
    "duration": "02:36",
    "artists": [
      { "name": "NONSENS", "link": "https://music.163.com/artist?id=1190100" },
      { "name": "Snavs", "link": "https://music.163.com/artist?id=1011006" }
    ],
    "album": {
      "name": "Golden",
      "link": "https://music.163.com/album?id=87321807"
    }
  },
  {
    "name": "Rebirth (feat. Ashley Apollodor)",
    "link": "https://music.163.com/song?id=41647488",
    "duration": "06:07",
    "artists": [
      { "name": "Rezonate", "link": "https://music.163.com/artist?id=837369" }
    ],
    "album": {
      "name": "Monstercat - Best of 2015",
      "link": "https://music.163.com/album?id=3451175"
    }
  },
  {
    "name": "Loverus",
    "link": "https://music.163.com/song?id=1432048250",
    "duration": "03:36",
    "artists": [
      {
        "name": "Tony Romera",
        "link": "https://music.163.com/artist?id=205396"
      }
    ],
    "album": {
      "name": "Loverus",
      "link": "https://music.163.com/album?id=86620261"
    }
  },
  {
    "name": "All That We Had Is Lost",
    "link": "https://music.163.com/song?id=26612937",
    "duration": "03:56",
    "artists": [
      {
        "name": "Postiljonen",
        "link": "https://music.163.com/artist?id=725356"
      }
    ],
    "album": {
      "name": "Skyer",
      "link": "https://music.163.com/album?id=2535635"
    }
  },
  {
    "name": "Dangerous (Oliver Remix)",
    "link": "https://music.163.com/song?id=31192433",
    "duration": "04:37",
    "artists": [
      { "name": "Big Data", "link": "https://music.163.com/artist?id=731016" }
    ],
    "album": {
      "name": "1.6 (Remixes)",
      "link": "https://music.163.com/album?id=3111260"
    }
  }
]
