[
  {
    "name": "Tell Me It's Okay",
    "link": "https://music.163.com/song?id=1465383614",
    "duration": "03:46",
    "artists": [
      { "name": "Fells", "link": "https://music.163.com/artist?id=57422" },
      {
        "name": "Kimmie Devereux",
        "link": "https://music.163.com/artist?id=28142870"
      }
    ],
    "album": {
      "name": "Tell Me It's Okay",
      "link": "https://music.163.com/album?id=92954313"
    }
  },
  {
    "name": "Want You",
    "link": "https://music.163.com/song?id=1383257166",
    "duration": "02:43",
    "artists": [
      { "name": "Erkki.R", "link": "https://music.163.com/artist?id=12901022" }
    ],
    "album": {
      "name": "Want You",
      "link": "https://music.163.com/album?id=80871782"
    }
  },
  {
    "name": "Remember Me",
    "link": "https://music.163.com/song?id=34834953",
    "duration": "03:25",
    "artists": [
      { "name": "Kozoro", "link": "https://music.163.com/artist?id=1050567" }
    ],
    "album": {
      "name": "Remember Me",
      "link": "https://music.163.com/album?id=3295700"
    }
  },
  {
    "name": "Everything Falls",
    "link": "https://music.163.com/song?id=17804651",
    "duration": "03:43",
    "artists": [
      { "name": "Fee", "link": "https://music.163.com/artist?id=57226" }
    ],
    "album": {
      "name": "Hope Rising",
      "link": "https://music.163.com/album?id=1639280"
    }
  },
  {
    "name": "Falling like the Stars",
    "link": "https://music.163.com/song?id=1363642270",
    "duration": "03:32",
    "artists": [
      {
        "name": "James Arthur",
        "link": "https://music.163.com/artist?id=673004"
      }
    ],
    "album": {
      "name": "Falling like the Stars",
      "link": "https://music.163.com/album?id=78960018"
    }
  },
  {
    "name": "Whatever It Takes",
    "link": "https://music.163.com/song?id=1470907433",
    "duration": "03:22",
    "artists": [
      {
        "name": "Imagine Dragons",
        "link": "https://music.163.com/artist?id=94779"
      }
    ],
    "album": {
      "name": "Best of 2018",
      "link": "https://music.163.com/album?id=93941420"
    }
  },
  {
    "name": "Wild Eyes (Radio Edit)",
    "link": "https://music.163.com/song?id=29747996",
    "duration": "03:24",
    "artists": [
      { "name": "Broiler", "link": "https://music.163.com/artist?id=886022" },
      { "name": "RAVVEL", "link": "https://music.163.com/artist?id=13190379" }
    ],
    "album": {
      "name": "Wild Eyes",
      "link": "https://music.163.com/album?id=3070536"
    }
  },
  {
    "name": "Smiling Down On Me",
    "link": "https://music.163.com/song?id=1423294",
    "duration": "03:14",
    "artists": [
      { "name": "Galen Crew", "link": "https://music.163.com/artist?id=34435" }
    ],
    "album": {
      "name": "Better Than a Fairy Tale",
      "link": "https://music.163.com/album?id=145852"
    }
  },
  {
    "name": "Rhythm In Me (Club Mix)",
    "link": "https://music.163.com/song?id=1451357900",
    "duration": "02:45",
    "artists": [
      {
        "name": "Pontifexx",
        "link": "https://music.163.com/artist?id=12387063"
      },
      { "name": "Duncan", "link": "https://music.163.com/artist?id=380358" },
      {
        "name": "Cammie Robinson",
        "link": "https://music.163.com/artist?id=13932261"
      },
      { "name": "2STRANGE", "link": "https://music.163.com/artist?id=33630240" }
    ],
    "album": {
      "name": "Rhythm In Me (Club Mix)",
      "link": "https://music.163.com/album?id=90038715"
    }
  },
  {
    "name": "Challenge",
    "link": "https://music.163.com/song?id=1306112076",
    "duration": "03:00",
    "artists": [
      {
        "name": "Lolo Zouaï",
        "link": "https://music.163.com/artist?id=13080302"
      }
    ],
    "album": {
      "name": "Challenge",
      "link": "https://music.163.com/album?id=72773357"
    }
  },
  {
    "name": "As long as it takes you",
    "link": "https://music.163.com/song?id=515796163",
    "duration": "03:05",
    "artists": [
      { "name": "keshi", "link": "https://music.163.com/artist?id=12544511" }
    ],
    "album": {
      "name": "As long as it takes you",
      "link": "https://music.163.com/album?id=36681119"
    }
  },
  {
    "name": "Loftið Verður Skyndilega Kalt",
    "link": "https://music.163.com/song?id=16139401",
    "duration": "05:48",
    "artists": [
      {
        "name": "Ólafur Arnalds",
        "link": "https://music.163.com/artist?id=40858"
      }
    ],
    "album": {
      "name": "…And They Have Escaped the Weight of Darkness",
      "link": "https://music.163.com/album?id=1489045"
    }
  },
  {
    "name": "One Direction Medley",
    "link": "https://music.163.com/song?id=464035016",
    "duration": "02:37",
    "artists": [
      {
        "name": "Anthem Lights",
        "link": "https://music.163.com/artist?id=86862"
      }
    ],
    "album": {
      "name": "I (Heart) Boy Bands",
      "link": "https://music.163.com/album?id=35241098"
    }
  },
  {
    "name": "Problema",
    "link": "https://music.163.com/song?id=1459504112",
    "duration": "02:20",
    "artists": [
      { "name": "Nevlin", "link": "https://music.163.com/artist?id=15022237" }
    ],
    "album": {
      "name": "Problema",
      "link": "https://music.163.com/album?id=91804518"
    }
  },
  {
    "name": "Friendship Is Magic",
    "link": "https://music.163.com/song?id=1399531193",
    "duration": "04:36",
    "artists": [
      {
        "name": "Marcus Warner",
        "link": "https://music.163.com/artist?id=1046308"
      }
    ],
    "album": {
      "name": "Reprise - EP",
      "link": "https://music.163.com/album?id=82782578"
    }
  },
  {
    "name": "Blood on the Dance Floor X Dangerous (The White Panda Mash-Up)",
    "link": "https://music.163.com/song?id=504425097",
    "duration": "03:38",
    "artists": [
      {
        "name": "Michael Jackson",
        "link": "https://music.163.com/artist?id=38853"
      },
      {
        "name": "The White Panda",
        "link": "https://music.163.com/artist?id=103172"
      }
    ],
    "album": {
      "name": "Blood on the Dance Floor X Dangerous (The White Panda Mash-Up)",
      "link": "https://music.163.com/album?id=36128338"
    }
  },
  {
    "name": "缺口",
    "link": "https://music.163.com/song?id=210870",
    "duration": "04:47",
    "artists": [
      { "name": "蔡琴", "link": "https://music.163.com/artist?id=7220" }
    ],
    "album": {
      "name": "鲍比达&蔡琴  遇见",
      "link": "https://music.163.com/album?id=21400"
    }
  },
  {
    "name": "Illusion",
    "link": "https://music.163.com/song?id=1383811881",
    "duration": "03:22",
    "artists": [
      { "name": "浮云心丶", "link": "https://music.163.com/artist?id=12350867" }
    ],
    "album": {
      "name": "Illusion",
      "link": "https://music.163.com/album?id=80884196"
    }
  },
  {
    "name": "曼彻斯特 (Manchester)",
    "link": "https://music.163.com/song?id=1482659613",
    "duration": "04:12",
    "artists": [
      { "name": "沈以诚", "link": "https://music.163.com/artist?id=12002248" }
    ],
    "album": {
      "name": "玩家 (Gamer)",
      "link": "https://music.163.com/album?id=88137146"
    }
  },
  {
    "name": "风雪梧桐",
    "link": "https://music.163.com/song?id=368742",
    "duration": "04:28",
    "artists": [
      { "name": "南拳妈妈", "link": "https://music.163.com/artist?id=12438" }
    ],
    "album": {
      "name": "决斗巴赫",
      "link": "https://music.163.com/album?id=36518"
    }
  },
  {
    "name": "Feels Like a Dream",
    "link": "https://music.163.com/song?id=1363342114",
    "duration": "04:19",
    "artists": [
      { "name": "Awakend", "link": "https://music.163.com/artist?id=13049055" },
      { "name": "Luma", "link": "https://music.163.com/artist?id=211460" },
      { "name": "Herrin", "link": "https://music.163.com/artist?id=12279436" }
    ],
    "album": {
      "name": "Feels Like a Dream",
      "link": "https://music.163.com/album?id=78935903"
    }
  },
  {
    "name": "Azure Galaxy-[Original Mix]-",
    "link": "https://music.163.com/song?id=487290168",
    "duration": "03:22",
    "artists": [
      { "name": "DJ Soviet", "link": "https://music.163.com/artist?id=999451" }
    ],
    "album": {
      "name": "Azure Galaxy [ HB.to巨蟹座们 ]",
      "link": "https://music.163.com/album?id=35676736"
    }
  },
  {
    "name": "春熙",
    "link": "https://music.163.com/song?id=455123462",
    "duration": "03:04",
    "artists": [
      { "name": "Wine-9", "link": "https://music.163.com/artist?id=12272786" }
    ],
    "album": {
      "name": "锦瑟",
      "link": "https://music.163.com/album?id=35136875"
    }
  },
  {
    "name": "Walking Blind",
    "link": "https://music.163.com/song?id=36783831",
    "duration": "03:21",
    "artists": [
      {
        "name": "Aidan Hawken",
        "link": "https://music.163.com/artist?id=28625"
      },
      {
        "name": "Carina Round",
        "link": "https://music.163.com/artist?id=51026"
      }
    ],
    "album": {
      "name": "Walking Blind",
      "link": "https://music.163.com/album?id=3403478"
    }
  },
  {
    "name": "Cornfield Chase（Piano Concerto Ver)",
    "link": "https://music.163.com/song?id=556748766",
    "duration": "02:06",
    "artists": [
      { "name": "6＆9", "link": "https://music.163.com/artist?id=12328829" }
    ],
    "album": {
      "name": "星际穿越",
      "link": "https://music.163.com/album?id=38520625"
    }
  },
  {
    "name": "Candy_Wind-英雄联盟（Nzzy remix）",
    "link": "https://music.163.com/song?id=1379855956",
    "duration": "03:10",
    "artists": [
      { "name": "Rye", "link": "https://music.163.com/artist?id=29234884" }
    ],
    "album": {
      "name": "英雄联盟",
      "link": "https://music.163.com/album?id=80468637"
    }
  },
  {
    "name": "Embrace",
    "link": "https://music.163.com/song?id=485354138",
    "duration": "04:36",
    "artists": [
      {
        "name": "Sappheiros",
        "link": "https://music.163.com/artist?id=11995187"
      }
    ],
    "album": {
      "name": "Embrace",
      "link": "https://music.163.com/album?id=35645354"
    }
  },
  {
    "name": "I'll Go On",
    "link": "https://music.163.com/song?id=419594778",
    "duration": "03:12",
    "artists": [
      { "name": "Yal!X", "link": "https://music.163.com/artist?id=1049671" }
    ],
    "album": {
      "name": "I'll Go On",
      "link": "https://music.163.com/album?id=34767245"
    }
  },
  {
    "name": "Hot Love",
    "link": "https://music.163.com/song?id=33252584",
    "duration": "03:12",
    "artists": [
      { "name": "LEISURE", "link": "https://music.163.com/artist?id=251595" }
    ],
    "album": {
      "name": "Hot Love",
      "link": "https://music.163.com/album?id=3190431"
    }
  },
  {
    "name": "Walking Trough The Rain",
    "link": "https://music.163.com/song?id=420125422",
    "duration": "07:12",
    "artists": [
      {
        "name": "Jay Hifive",
        "link": "https://music.163.com/artist?id=11978028"
      }
    ],
    "album": {
      "name": "Walking Trough The Rain",
      "link": "https://music.163.com/album?id=34767434"
    }
  }
]
